crypto_markets.libs/libselinux-0922c95c.so.1
crypto_markets.libs/libpcre-9513aab5.so.1.2.0
crypto_markets.libs/libcrypto-ddbcb6f7.so.1.0.2k
crypto_markets.libs/libkrb5-fc820a1d.so.3.3
crypto_markets.libs/libcom_err-2abe824b.so.2.1
crypto_markets.libs/libkeyutils-dfe70bd6.so.1.5
crypto_markets.libs/libk5crypto-b1f99d5c.so.3.1
crypto_markets.libs/libssl-e9dd7f6d.so.1.0.2k
crypto_markets.libs/libgssapi_krb5-497db0c6.so.2.2
crypto_markets.libs/libkrb5support-a4e68a84.so.0.1
crypto_markets/_lowlevel__lib.so
crypto_markets/_lowlevel__ffi.py
crypto_markets/__init__.py
crypto_markets/_lowlevel.py
crypto_markets-1.0.5.dist-info/WHEEL
crypto_markets-1.0.5.dist-info/METADATA
crypto_markets-1.0.5.dist-info/RECORD
crypto_markets-1.0.5.dist-info/top_level.txt
crypto_markets-1.0.5.dist-info/LICENSE
