Metadata-Version: 2.1
Name: crypto-markets
Version: 1.0.5
Summary: Fetch trading markets from a cryptocurrency exchange
Home-page: https://github.com/soulmachine/crypto-markets-py
Author: soulmachine
License: Apache License 2.0
Keywords: blockchain,cryptocurrency,trading
Platform: UNKNOWN
Classifier: Programming Language :: Python :: 3.6
Classifier: License :: OSI Approved :: Apache Software License
Classifier: Topic :: Software Development :: Libraries :: Python Modules
Requires-Python: >=3.6
License-File: LICENSE
Requires-Dist: cffi
